tbxforms/__init__.py
tbxforms/apps.py
tbxforms/choices.py
tbxforms/fields.py
tbxforms/forms.py
tbxforms/helper.py
tbxforms/layout/__init__.py
tbxforms/layout/base.py
tbxforms/layout/buttons.py
tbxforms/layout/constants.py
tbxforms/layout/containers.py
tbxforms/layout/content.py
tbxforms/layout/fields.py
tbxforms/static/js/tbxforms.js
tbxforms/static/sass/_conditional.scss
tbxforms/static/sass/govuk/_base.scss
tbxforms/static/sass/govuk/components/character-count/_character-count.scss
tbxforms/static/sass/govuk/components/character-count/_index.scss
tbxforms/static/sass/govuk/components/checkboxes/_checkboxes.scss
tbxforms/static/sass/govuk/components/checkboxes/_index.scss
tbxforms/static/sass/govuk/components/date-input/_date-input.scss
tbxforms/static/sass/govuk/components/date-input/_index.scss
tbxforms/static/sass/govuk/components/error-message/_error-message.scss
tbxforms/static/sass/govuk/components/error-message/_index.scss
tbxforms/static/sass/govuk/components/error-summary/_error-summary.scss
tbxforms/static/sass/govuk/components/error-summary/_index.scss
tbxforms/static/sass/govuk/components/fieldset/_fieldset.scss
tbxforms/static/sass/govuk/components/fieldset/_index.scss
tbxforms/static/sass/govuk/components/file-upload/_file-upload.scss
tbxforms/static/sass/govuk/components/file-upload/_index.scss
tbxforms/static/sass/govuk/components/hint/_hint.scss
tbxforms/static/sass/govuk/components/hint/_index.scss
tbxforms/static/sass/govuk/components/input/_index.scss
tbxforms/static/sass/govuk/components/input/_input.scss
tbxforms/static/sass/govuk/components/label/_index.scss
tbxforms/static/sass/govuk/components/label/_label.scss
tbxforms/static/sass/govuk/components/password-input/_index.scss
tbxforms/static/sass/govuk/components/password-input/_password-input.scss
tbxforms/static/sass/govuk/components/radios/_index.scss
tbxforms/static/sass/govuk/components/radios/_radios.scss
tbxforms/static/sass/govuk/components/select/_index.scss
tbxforms-4.3.1.dist-info/LICENSE
tbxforms-4.3.1.dist-info/METADATA
tbxforms-4.3.1.dist-info/WHEEL
tbxforms-4.3.1.dist-info/RECORD
