Metadata-Version: 2.1
Name: tbxforms
Version: 4.3.1
Summary: A Torchbox-flavoured template pack for django-crispy-forms, adapted from crispy-forms-gds
Home-page: https://github.com/torchbox/tbxforms/
License: BSD-2-Clause
Keywords: crispy,django,django crispy forms,django crispy form,forms,gds,tbxforms,wagtail,wagtail forms,wagtail form
Author: Kyle Bayler
Author-email: kyle.bayler@torchbox.com
Requires-Python: >=3.8.1,<4.0
Classifier: Development Status :: 3 - Alpha
Classifier: Environment :: Web Environment
Classifier: Framework :: Django
Classifier: Framework :: Django :: 3.2
Classifier: Framework :: Django :: 4.0
Classifier: Framework :: Django :: 4.1
Classifier: Framework :: Django :: 4.2
Classifier: Framework :: Django :: 5.0
Classifier: Framework :: Wagtail
Classifier: Framework :: Wagtail :: 2
Classifier: Framework :: Wagtail :: 3
Classifier: Framework :: Wagtail :: 4
Classifier: Framework :: Wagtail :: 5
Classifier: Intended Audience :: Developers
Classifier: License :: OSI Approved :: BSD License
Classifier: Operating System :: OS Independent
Classifier: Programming Language :: Python :: 3
Classifier: Programming Language :: Python :: 3.9
Classifier: Programming Language :: Python :: 3.10
Classifier: Programming Language :: Python :: 3.11
Classifier: Programming Language :: Python :: 3.12
Classifier: Programming Language :: Python :: 3 :: Only
Classifier: Programming Language :: Python :: 3.8
Requires-Dist: Django (>=3.2)
Requires-Dist: django-crispy-forms (>=2.1,<3.0)
Project-URL: Repository, https://github.com/torchbox/tbxforms/
